walletone/__init__.py
walletone/apps.py
walletone/forms.py
walletone/models.py
walletone/settings.py
walletone/signals.py
walletone/urls.py
walletone/views.py
walletone/migrations/0001_initial.py
walletone/migrations/0002_auto_20160421_1941.py
walletone/migrations/__init__.py
django_walletone-1.0.0a5.dist-info/top_level.txt
django_walletone-1.0.0a5.dist-info/METADATA
django_walletone-1.0.0a5.dist-info/DESCRIPTION.rst
django_walletone-1.0.0a5.dist-info/metadata.json
django_walletone-1.0.0a5.dist-info/WHEEL
django_walletone-1.0.0a5.dist-info/RECORD
