Metadata-Version: 2.0
Name: django-walletone
Version: 1.0.0a5
Summary: WalletOne payment system integration in Django.
Home-page: https://github.com/otov4its/django-walletone
Author: Stanislav Otovchits
Author-email: otov4its@gmail.com
License: MIT
Keywords: django,walletone,w1
Platform: UNKNOWN
Classifier: Development Status :: 3 - Alpha
Classifier: Framework :: Django
Classifier: Intended Audience :: Developers
Classifier: Intended Audience :: System Administrators
Classifier: License :: OSI Approved :: MIT License
Classifier: Operating System :: OS Independent
Classifier: Topic :: Software Development
Classifier: Programming Language :: Python :: 2
Classifier: Programming Language :: Python :: 2.7
Classifier: Programming Language :: Python :: 3
Classifier: Programming Language :: Python :: 3.4
Requires-Dist: Django (>=1.7)
